[
  {
    "id": "INV_20250801_074533",
    "invoice_number": "INV-20250801-074533",
    "client_id": "CLIENT_20250801_073335",
    "inspection_id": null,
    "industry_type": "automotive",
    "issue_date": "2025-08-01",
    "due_date": "2025-08-31",
    "status": "draft",
    "jobs": [],
    "items": [
      {
        "id": "item_1",
        "job_id": null,
        "item_type": "parts",
        "description": "VSI2",
        "quantity": "1",
        "unit_price": "19.99",
        "unit": "item",
        "tax_rate": "8",
        "discount_percent": "5",
        "notes": "",
        "subtotal": "19.99",
        "discount_amount": "0.9995",
        "taxable_amount": "18.9905",
        "tax_amount": "1.51924",
        "total": "20.50974"
      },
      {
        "id": "item_2",
        "job_id": null,
        "item_type": "parts",
        "description": "AC2",
        "quantity": "1",
        "unit_price": "149.99",
        "unit": "item",
        "tax_rate": "8",
        "discount_percent": "0",
        "notes": "",
        "subtotal": "149.99",
        "discount_amount": "0",
        "taxable_amount": "149.99",
        "tax_amount": "11.9992",
        "total": "161.9892"
      },
      {
        "id": "item_3",
        "job_id": null,
        "item_type": "materials",
        "description": "SHOP",
        "quantity": "6",
        "unit_price": "3.99",
        "unit": "item",
        "tax_rate": "0",
        "discount_percent": "0",
        "notes": "",
        "subtotal": "23.94",
        "discount_amount": "0",
        "taxable_amount": "23.94",
        "tax_amount": "0",
        "total": "23.94"
      },
      {
        "id": "item_4",
        "job_id": null,
        "item_type": "materials",
        "description": "134a",
        "quantity": "1.3",
        "unit_price": "39.99",
        "unit": "item",
        "tax_rate": "8",
        "discount_percent": "0",
        "notes": "",
        "subtotal": "51.987",
        "discount_amount": "0",
        "taxable_amount": "51.987",
        "tax_amount": "4.15896",
        "total": "56.14596"
      }
    ],
    "subtotal": "244.909",
    "tax_amount": "17.677400",
    "discount_amount": "0.9995",
    "total": "261.586900",
    "labor_total": "0",
    "parts_total": "182.49894",
    "materials_total": "80.08596",
    "service_total": "0",
    "shipping": "0",
    "handling": "0",
    "other_charges": "0",
    "terms": "",
    "notes": "",
    "footer": null,
    "created_at": "2025-08-01 07:45:33.884836",
    "updated_at": "2025-08-01 07:45:33.884841",
    "sent_at": null,
    "paid_at": null,
    "payments": []
  },
  {
    "id": "INV_20250801_082036",
    "invoice_number": "INV-20250801-082036",
    "client_id": "CLIENT_20250801_073335",
    "inspection_id": "543543",
    "industry_type": "automotive",
    "issue_date": "2025-08-01",
    "due_date": "2025-08-31",
    "status": "draft",
    "jobs": [
      {
        "id": "JOB_20250801_082036_1",
        "name": "Brake System Service",
        "description": "Complete brake system inspection and maintenance",
        "job_number": "BRK-001",
        "start_date": null,
        "completion_date": null,
        "status": "completed",
        "notes": null,
        "created_at": "2025-08-01 08:20:36.329912",
        "updated_at": "2025-08-01 08:20:36.329913"
      },
      {
        "id": "JOB_20250801_082036_2",
        "name": "Engine Tune-Up",
        "description": "Engine performance optimization and maintenance",
        "job_number": "ENG-002",
        "start_date": null,
        "completion_date": null,
        "status": "completed",
        "notes": null,
        "created_at": "2025-08-01 08:20:36.329946",
        "updated_at": "2025-08-01 08:20:36.329947"
      },
      {
        "id": "JOB_20250801_082036_3",
        "name": "Electrical System Diagnosis",
        "description": "Electrical system troubleshooting and repair",
        "job_number": "ELEC-003",
        "start_date": null,
        "completion_date": null,
        "status": "completed",
        "notes": null,
        "created_at": "2025-08-01 08:20:36.329963",
        "updated_at": "2025-08-01 08:20:36.329963"
      }
    ],
    "items": [
      {
        "id": "item_1",
        "job_id": "JOB_20250801_082036_1",
        "item_type": "labor",
        "description": "Brake System Inspection & Service",
        "quantity": "2.5",
        "unit_price": "75",
        "unit": "hours",
        "tax_rate": "8.5",
        "discount_percent": "0",
        "notes": "Complete brake system inspection and pad replacement",
        "subtotal": "187.5",
        "discount_amount": "0",
        "taxable_amount": "187.5",
        "tax_amount": "15.9375",
        "total": "203.4375"
      },
      {
        "id": "item_2",
        "job_id": "JOB_20250801_082036_1",
        "item_type": "parts",
        "description": "Brake Pads (Front)",
        "quantity": "1",
        "unit_price": "89.99",
        "unit": "set",
        "tax_rate": "8.5",
        "discount_percent": "0",
        "notes": "Premium ceramic brake pads",
        "subtotal": "89.99",
        "discount_amount": "0",
        "taxable_amount": "89.99",
        "tax_amount": "7.64915",
        "total": "97.63915"
      },
      {
        "id": "item_3",
        "job_id": "JOB_20250801_082036_1",
        "item_type": "parts",
        "description": "Brake Rotors (Front)",
        "quantity": "2",
        "unit_price": "45",
        "unit": "each",
        "tax_rate": "8.5",
        "discount_percent": "0",
        "notes": "OEM replacement rotors",
        "subtotal": "90",
        "discount_amount": "0",
        "taxable_amount": "90",
        "tax_amount": "7.65",
        "total": "97.65"
      },
      {
        "id": "item_4",
        "job_id": "JOB_20250801_082036_2",
        "item_type": "labor",
        "description": "Engine Tune-Up Service",
        "quantity": "1.5",
        "unit_price": "85",
        "unit": "hours",
        "tax_rate": "8.5",
        "discount_percent": "0",
        "notes": "Spark plug replacement and engine optimization",
        "subtotal": "127.5",
        "discount_amount": "0",
        "taxable_amount": "127.5",
        "tax_amount": "10.8375",
        "total": "138.3375"
      },
      {
        "id": "item_5",
        "job_id": "JOB_20250801_082036_2",
        "item_type": "parts",
        "description": "Spark Plugs",
        "quantity": "4",
        "unit_price": "12.5",
        "unit": "each",
        "tax_rate": "8.5",
        "discount_percent": "0",
        "notes": "Iridium spark plugs",
        "subtotal": "50",
        "discount_amount": "0",
        "taxable_amount": "50",
        "tax_amount": "4.25",
        "total": "54.25"
      },
      {
        "id": "item_6",
        "job_id": "JOB_20250801_082036_2",
        "item_type": "parts",
        "description": "Air Filter",
        "quantity": "1",
        "unit_price": "18",
        "unit": "each",
        "tax_rate": "8.5",
        "discount_percent": "0",
        "notes": "High-performance air filter",
        "subtotal": "18",
        "discount_amount": "0",
        "taxable_amount": "18",
        "tax_amount": "1.53",
        "total": "19.53"
      },
      {
        "id": "item_7",
        "job_id": "JOB_20250801_082036_3",
        "item_type": "labor",
        "description": "Electrical System Diagnosis",
        "quantity": "1",
        "unit_price": "95",
        "unit": "hour",
        "tax_rate": "8.5",
        "discount_percent": "0",
        "notes": "Computer diagnostic and troubleshooting",
        "subtotal": "95",
        "discount_amount": "0",
        "taxable_amount": "95",
        "tax_amount": "8.075",
        "total": "103.075"
      },
      {
        "id": "item_8",
        "job_id": "JOB_20250801_082036_3",
        "item_type": "parts",
        "description": "Battery",
        "quantity": "1",
        "unit_price": "125",
        "unit": "each",
        "tax_rate": "8.5",
        "discount_percent": "0",
        "notes": "Heavy-duty automotive battery",
        "subtotal": "125",
        "discount_amount": "0",
        "taxable_amount": "125",
        "tax_amount": "10.625",
        "total": "135.625"
      },
      {
        "id": "item_9",
        "job_id": null,
        "item_type": "service",
        "description": "Comprehensive Vehicle Inspection",
        "quantity": "1",
        "unit_price": "150",
        "unit": "inspection",
        "tax_rate": "8.5",
        "discount_percent": "0",
        "notes": "Full vehicle safety and condition assessment",
        "subtotal": "150",
        "discount_amount": "0",
        "taxable_amount": "150",
        "tax_amount": "12.75",
        "total": "162.75"
      },
      {
        "id": "item_10",
        "job_id": null,
        "item_type": "service",
        "description": "Oil Change & Filter",
        "quantity": "1",
        "unit_price": "45",
        "unit": "service",
        "tax_rate": "8.5",
        "discount_percent": "0",
        "notes": "Synthetic oil and premium filter",
        "subtotal": "45",
        "discount_amount": "0",
        "taxable_amount": "45",
        "tax_amount": "3.825",
        "total": "48.825"
      }
    ],
    "subtotal": "977.99",
    "tax_amount": "83.12915",
    "discount_amount": "0.00",
    "total": "1061.11915",
    "labor_total": "410.0",
    "parts_total": "372.99",
    "materials_total": 0,
    "service_total": "195",
    "shipping": "0",
    "handling": "0",
    "other_charges": "0",
    "terms": "Payment due within 30 days. Late payments subject to 1.5% monthly interest.",
    "notes": "All work performed to industry standards. Warranty applies to parts and labor as specified.",
    "footer": null,
    "created_at": "2025-08-01 08:20:36.329885",
    "updated_at": "2025-08-01 08:20:36.329888",
    "sent_at": null,
    "paid_at": null,
    "payments": []
  },
  {
    "id": "INV_20250801_082146",
    "invoice_number": "INV-20250801-082146",
    "client_id": "CLIENT_20250801_073335",
    "inspection_id": null,
    "industry_type": "automotive",
    "issue_date": "2025-08-01",
    "due_date": "2025-08-31",
    "status": "draft",
    "jobs": [
      {
        "id": "JOB_20250801_082146_1",
        "name": "Test Job",
        "description": "Test job description",
        "job_number": "TEST-001",
        "start_date": null,
        "completion_date": null,
        "status": "completed",
        "notes": null,
        "created_at": "2025-08-01 08:21:46.208101",
        "updated_at": "2025-08-01 08:21:46.208102"
      }
    ],
    "items": [
      {
        "id": "item_1",
        "job_id": null,
        "item_type": "labor",
        "description": "Test Labor",
        "quantity": "2",
        "unit_price": "50",
        "unit": "hours",
        "tax_rate": "0",
        "discount_percent": "0",
        "notes": "Test item",
        "subtotal": "100",
        "discount_amount": "0",
        "taxable_amount": "100",
        "tax_amount": "0",
        "total": "100"
      }
    ],
    "subtotal": "100",
    "tax_amount": "0",
    "discount_amount": "0",
    "total": "100",
    "labor_total": "100",
    "parts_total": 0,
    "materials_total": 0,
    "service_total": 0,
    "shipping": "0",
    "handling": "0",
    "other_charges": "0",
    "terms": "Payment due in 30 days",
    "notes": "Test invoice",
    "footer": null,
    "created_at": "2025-08-01 08:21:46.208078",
    "updated_at": "2025-08-01 08:21:46.208081",
    "sent_at": null,
    "paid_at": null,
    "payments": []
  }
]