{
  "1HGBH41JXMN109186": {
    "Results": [
      {"Variable": "Model Year", "Value": "1991"},
      {"Variable": "Make", "Value": "HONDA"},
      {"Variable": "Model", "Value": "ACCORD"},
      {"Variable": "Trim", "Value": "DX"},
      {"Variable": "Displacement (L)", "Value": "2.2"},
      {"Variable": "Transmission Style", "Value": "Automatic"},
      {"Variable": "Body Style", "Value": "Sedan"},
      {"Variable": "Fuel Type - Primary", "Value": "Gasoline"},
      {"Variable": "Drive Type", "Value": "FWD"},
      {"Variable": "Plant Country", "Value": "USA"},
      {"Variable": "Plant Code", "Value": "H"},
      {"Variable": "Series", "Value": "ACCORD"}
    ]
  },
  "1G1ZT51806F123456": {
    "Results": [
      {"Variable": "Model Year", "Value": "2006"},
      {"Variable": "Make", "Value": "CHEVROLET"},
      {"Variable": "Model", "Value": "CORVETTE"},
      {"Variable": "Trim", "Value": "Z06"},
      {"Variable": "Displacement (L)", "Value": "7.0"},
      {"Variable": "Transmission Style", "Value": "Manual"},
      {"Variable": "Body Style", "Value": "Coupe"},
      {"Variable": "Fuel Type - Primary", "Value": "Gasoline"},
      {"Variable": "Drive Type", "Value": "RWD"},
      {"Variable": "Plant Country", "Value": "USA"},
      {"Variable": "Plant Code", "Value": "B"},
      {"Variable": "Series", "Value": "CORVETTE"}
    ]
  },
  "WBA3B5C50FD123456": {
    "Results": [
      {"Variable": "Model Year", "Value": "2015"},
      {"Variable": "Make", "Value": "BMW"},
      {"Variable": "Model", "Value": "3 SERIES"},
      {"Variable": "Trim", "Value": "328i"},
      {"Variable": "Displacement (L)", "Value": "2.0"},
      {"Variable": "Transmission Style", "Value": "Automatic"},
      {"Variable": "Body Style", "Value": "Sedan"},
      {"Variable": "Fuel Type - Primary", "Value": "Gasoline"},
      {"Variable": "Drive Type", "Value": "RWD"},
      {"Variable": "Plant Country", "Value": "Germany"},
      {"Variable": "Plant Code", "Value": "F"},
      {"Variable": "Series", "Value": "3 SERIES"}
    ]
  },
  "5NPE34AF4FH123456": {
    "Results": [
      {"Variable": "Model Year", "Value": "2015"},
      {"Variable": "Make", "Value": "HYUNDAI"},
      {"Variable": "Model", "Value": "SONATA"},
      {"Variable": "Trim", "Value": "Sport"},
      {"Variable": "Displacement (L)", "Value": "2.4"},
      {"Variable": "Transmission Style", "Value": "Automatic"},
      {"Variable": "Body Style", "Value": "Sedan"},
      {"Variable": "Fuel Type - Primary", "Value": "Gasoline"},
      {"Variable": "Drive Type", "Value": "FWD"},
      {"Variable": "Plant Country", "Value": "USA"},
      {"Variable": "Plant Code", "Value": "M"},
      {"Variable": "Series", "Value": "SONATA"}
    ]
  }
} 